cs/sharedfile.py
cs.sharedfile-20230212.dist-info/METADATA
cs.sharedfile-20230212.dist-info/WHEEL
cs.sharedfile-20230212.dist-info/top_level.txt
cs.sharedfile-20230212.dist-info/RECORD
