Metadata-Version: 2.1
Name: cs.sharedfile
Version: 20230212
Summary: facilities for shared access to files
Home-page: https://bitbucket.org/cameron_simpson/css/commits/all
Author: Cameron Simpson
Author-email: Cameron Simpson <cs@cskk.id.au>
License: GNU General Public License v3 or later (GPLv3+)
Project-URL: URL, https://bitbucket.org/cameron_simpson/css/commits/all
Keywords: python2,python3
Classifier: Programming Language :: Python
Classifier: Programming Language :: Python :: 2
Classifier: Programming Language :: Python :: 3
Classifier: Development Status :: 4 - Beta
Classifier: Intended Audience :: Developers
Classifier: Operating System :: OS Independent
Classifier: Topic :: Software Development :: Libraries :: Python Modules
Classifier: License :: OSI Approved :: GNU General Public License v3 or later (GPLv3+)
Requires-Dist: cs.filestate (>=20181107)
Requires-Dist: cs.gimmicks (>=20211208)
Requires-Dist: cs.lex (>=20230210)
Requires-Dist: cs.pfx (>=20221118)
Requires-Dist: cs.range (>=20190102)
